setup.py
SuperQuant/__init__.py
SuperQuant.egg-info/PKG-INFO
SuperQuant.egg-info/SOURCES.txt
SuperQuant.egg-info/dependency_links.txt
SuperQuant.egg-info/top_level.txt
SuperQuant.egg-info/zip-safe