Metadata-Version: 1.1
Name: SuperQuant
Version: 0.0.31.dev0
Summary: SuperQuant:Quantitative Financial Strategy Framework
Home-page: https://github.com/Fengbrain/SuperQuant
Author: Junfeng Li
Author-email: 617644591@qq.com
License: MIT
Keywords: SuperQuant,quant,finance,Backtest,Framework
Platform: UNKNOWN
Classifier: License :: OSI Approved :: MIT License
Classifier: Programming Language :: Python
Classifier: Intended Audience :: Developers
Classifier: Operating System :: OS Independent
